Workbook

Sheet Start here
B2: Principal wellbeing funding - email response builder
B3: Triage a query with the decision-making framework and generate a draft reply
B5: How to use this tool
C6: 1. Open the 'Email builder' tab.
C7: 2. Step 1 - choose a greeting and add the recipient's name and the topic of their query.
C8: 3. Step 2 - if it is a recurring query (physiotherapy, travel, pooling funds, etc.), pick a common response from the dropdown. Done!
C9: 4. Step 3 - otherwise, answer the six decision-making framework questions (plus the two routing questions) using the Yes / No / Maybe dropdowns.
C10: 5. Step 4 - click the draft email cell, press Ctrl+C, paste into Outlook, and fine-tune before sending.
B12: Tips
C13: * You do not need to answer every question - the draft only includes paragraphs for the questions you have answered.
C14: * To clear an answer, select the cell and press Delete.
C15: * The wording lives on the 'Response library' and 'Common responses' tabs - edit the yellow columns there and the drafts update automatically.
C16: * The draft is a starting point: add case-specific detail and always confirm the advice against the current Ikon guidance before sending.
B18: Contact
C19: Principal wellbeing expenditure support | 9264 4201 | whsw.staffwellbeing@education.wa.edu.au
C21: This information is correct as at July 2026. Always refer to Ikon for the most up-to-date information.

Sheet Email builder
B2: Principal wellbeing funding - email response builder
B3: Answer the questions below, then copy the draft email from Step 4
B5: STEP 1 · Query details
C6: Greeting | D6: Good morning | F6: Opens the email.
C7: Recipient name (optional) | F7: Personalises the greeting, e.g. "Good morning Damien,"
C8: Topic of the query (optional) | F8: Completes "Thank you for reaching out regarding ..." - e.g. "using the funding for physiotherapy"
B10: STEP 2 · Recurring query? Pick a common response (optional)
C11: Common response | D11: Build from the framework questions
C12: Leave as 'Build from the framework questions' to build the reply from Step 3 instead.
B14: STEP 3 · Answer the framework questions (skip if you picked a common response)
C15: Select Yes, No or Maybe. Unanswered questions are simply left out of the draft.
B16: Q1 | C16: Will this directly benefit the principal's health, wellbeing or both?
B17: Q2 | C17: Does this align with the priorities in the health and wellbeing strategies or panel service categories?
B18: Q3 | C18: Would this expenditure uphold Department values and standards, as per the Integrity framework and Code of Conduct?
B19: Q4 | C19: Is the provider reputable, appropriately insured and qualified to deliver the service?
B20: Q5 | C20: Does this service meet a need that cannot be provided for by current Department programs or services?
B21: Q6 | C21: Have all supplier-related conflicts of interest been identified, reported and appropriately managed (or do none apply)?
C22: Extra routing questions - these add procurement / travel wording to the draft:
B23: Panel | C23: Does this align with the panel of wellbeing service providers?
B24: Travel | C24: Does this involve travel or accommodation?
B26: TRIAGE RESULT
B27: =Lists!F13
B29: STEP 4 · Your draft email
C30: Click the draft below, press Ctrl+C to copy, then paste into Outlook. Add case-specific detail and confirm against current Ikon guidance before sending.
B31: =Lists!F12

Sheet Response library
A1: Response library - modular paragraphs for the question-built draft
A2: Edit the yellow 'Draft email paragraph' column to change the wording. Do not edit column E (lookup key).
A4: Code | B4: Question | C4: Answer | D4: Draft email paragraph - edit this yellow column | E4: Lookup key
A5: Q1 | B5: Will this directly benefit the principal's health, wellbeing or both? | C5: Yes | D5: The proposed expenditure meets the first test of the decision-making framework: it is intended to directly benefit your health, wellbeing or both as a principal. | E5: =A5&"|"&C5
A6: Q1 | B6: Will this directly benefit the principal's health, wellbeing or both? | C6: No | D6: The proposed expenditure does not appear to directly benefit your health or wellbeing as a principal. The targeted funding is to address your needs as a principal - it is not intended for staff wellbeing or general operating costs - so we recommend reconsidering this expenditure. | E6: =A6&"|"&C6
A7: Q1 | B7: Will this directly benefit the principal's health, wellbeing or both? | C7: Maybe | D7: It is not clear that this would directly benefit your health or wellbeing as a principal. We would be happy to talk this through with you before you proceed. | E7: =A7&"|"&C7
A8: Q2 | B8: Does this align with the priorities in the health and wellbeing strategies or panel service categories? | C8: Yes | D8: It aligns with the priorities in the health and wellbeing strategies and the panel service categories (executive and leadership coaching, executive health assessment, and mental health support). | E8: =A8&"|"&C8
A9: Q2 | B9: Does this align with the priorities in the health and wellbeing strategies or panel service categories? | C9: No | D9: It does not align with the priorities in the health and wellbeing strategies or the panel service categories, so we recommend reconsidering this expenditure. | E9: =A9&"|"&C9
A10: Q2 | B10: Does this align with the priorities in the health and wellbeing strategies or panel service categories? | C10: Maybe | D10: The alignment with the health and wellbeing strategies or the panel service categories is not clear - please check with us before proceeding. | E10: =A10&"|"&C10
A11: Q3 | B11: Would this expenditure uphold Department values and standards, as per the Integrity framework and Code of Conduct? | C11: Yes | D11: The expenditure would uphold Department values and standards, in line with our Integrity framework and Code of Conduct (including Standard 8 - use public resources responsibly). | E11: =A11&"|"&C11
A12: Q3 | B12: Would this expenditure uphold Department values and standards, as per the Integrity framework and Code of Conduct? | C12: No | D12: The expenditure does not appear to uphold Department values and standards under the Integrity framework and Code of Conduct, so we recommend reconsidering it. | E12: =A12&"|"&C12
A13: Q3 | B13: Would this expenditure uphold Department values and standards, as per the Integrity framework and Code of Conduct? | C13: Maybe | D13: It is not clear that the expenditure would uphold Department values and standards under the Integrity framework and Code of Conduct - please contact us before proceeding. | E13: =A13&"|"&C13
A14: Q4 | B14: Is the provider reputable, appropriately insured and qualified to deliver the service? | C14: Yes | D14: The provider is reputable, appropriately insured and qualified to deliver the service. | E14: =A14&"|"&C14
A15: Q4 | B15: Is the provider reputable, appropriately insured and qualified to deliver the service? | C15: No | D15: The provider's qualifications, insurance or reputation cannot be confirmed, so please do not proceed until this is resolved. Information about managing provider risks is available in the Develop a staff health and wellbeing plan Ikon service. | E15: =A15&"|"&C15
A16: Q4 | B16: Is the provider reputable, appropriately insured and qualified to deliver the service? | C16: Maybe | D16: The provider's qualifications, insurance or reputation have not yet been confirmed. Where relevant, check the Australian Health Practitioner Regulation Agency (AHPRA) register and confirm the provider's insurance before proceeding. | E16: =A16&"|"&C16
... A26: Travel | B26: Does this involve travel or accommodation? | C26: Yes | D26: As the query involves travel or accommodation: the funding may be used for travel and accommodation where it is required to support access to an eligible principal wellbeing activity, in line with the Official Travel Policy and the associated Official Air Travel and Travel Accommodation, Meal and Other Expenses procedures. Travellers cannot approve their own travel - please seek approval from an Assistant Director of Education or above prior to booking. The funding is not intended to be used solely for travel or accommodation. | E26: =A26&"|"&C26
A27: Travel | B27: Does this involve travel or accommodation? | C27: No | E27: =A27&"|"&C27
A28: Travel | B28: Does this involve travel or accommodation? | C28: Maybe | D28: If travel or accommodation ends up being involved, it may be funded where it supports the eligible wellbeing activity, in line with the Official Travel Policy - please check the approval requirements with us before booking. | E28: =A28&"|"&C28

Sheet Common responses
A1: Common responses - full reply bodies for recurring queries
A2: These appear in the Step 2 dropdown on the Email builder tab. Edit the yellow text (or the option names) and the tool updates automatically. The greeting, thank-you line and sign-off are added by the builder - only write the body here.
A4: Response option (appears in the dropdown) | B4: Draft email body - edit this yellow column
A5: Treatments and therapies (e.g. physiotherapy) - not in scope | B5: To answer briefly: no - personal health care, treatments and therapies (including physiotherapy and chiropractic care) are not within the scope of the targeted wellbeing funding. To answer more thoroughly: The Workers' Compensation and Injury Management Act 2023 (WA) prohibits employers from diverting workers away from making a claim, so wellbeing funds cannot be used for injury-related assessment or treatment services. Treatment for work-related pain or injury may be available through the workers' compensation process, and may include payment for expenses, loss of earnings or both. Personal medical expenses are considered a fringe benefit. While this service falls outside the scope of the funding, there are a range of other services you may wish to consider, including professional learning and resilience training, mental health support or pastoral care, coaching or mentoring (including executive and wellbeing coaching), and executive health and wellbeing assessments.
A6: Memberships, gym, goods or devices - not in scope | B6: To answer briefly: no - memberships (such as gym or Pilates memberships), goods and personal devices are for the personal benefit of the employee, are considered a fringe benefit, and are not within the scope of the targeted wellbeing funding. You may instead wish to consider services such as professional learning and resilience training, mental health support or pastoral care, coaching or mentoring (including executive and wellbeing coaching), or an executive health and wellbeing assessment.
A7: Travel and accommodation - in scope with conditions | B7: To answer briefly: yes - the wellbeing funding can be used toward travel and accommodation needed to support access to an eligible wellbeing activity (such as professional learning, a professional conference or similar). To answer more thoroughly: The funding may be used for travel and accommodation where the travel is required to support the wellbeing activity. It is not intended to be used solely for travel or accommodation. Travel needs to align with the Official Travel Policy and the associated Official Air Travel and Travel Accommodation, Meal and Other Expenses procedures. Travellers cannot approve their own travel: per the Travel Approval Schedule, please seek approval from an Assistant Director of Education or above prior to booking. For domestic air travel, the domestic air travel application form must be completed and approved before booking.
A8: Conference or professional learning - in scope with conditions | B8: To answer briefly: yes - conferences and professional learning are considered appropriate expenditure where the majority of the program focuses on enhancing leadership capability and includes wellbeing topics for executives. To answer more thoroughly: Suitable themes include work-related stress reduction, managing workload and role overload, resilience skills for leaders, decision-making under stress, and high-performance leadership without burnout. The targeted funding may complement your school's budget allocation for the principal's professional learning, and relevant travel costs, but it should not replace it. If travel is required to attend, it needs to align with the Official Travel Policy and associated procedures, with approval from an Assistant Director of Education or above prior to booking.
A9: Pooling funding with other schools - supported | B9: To answer briefly: yes - you may choose to pool your wellbeing funding with other schools, such as those in your school network, to access higher cost support services (for example, leadership or wellbeing coaching). To answer more thoroughly: The decision-making framework applies to pooled funding in the same way as individual funding. You can choose an appropriate budget account or accounts to record the transfer of funds when pooling resources. For purchases under $50,000, follow the Buy goods and services under $50,000 Ikon service - the Verbal quotation template or Very simple purchase template may be useful. Purchases of less than $5,000 are considered low-value procurements and a panel is not required, provided value for money has been considered.
A10: Recording purchases and acquittal - guidance | B10: To answer briefly: expenditure only needs to be lodged through Oracle, and you can choose an appropriate budget account or accounts to record purchases against. We do not monitor principal wellbeing expenditure, and you do not need to provide formal acquittal reports. We do encourage you to keep a record of your decisions to demonstrate accountable and ethical decision-making - the Manage school accounting records Ikon service provides guidance on record keeping.
A11: Ergonomic assessment or equipment - school budget | B11: To answer briefly: ergonomic assessments and equipment are provided for in existing school funding, so they sit outside the targeted wellbeing funding. For guidance, refer to the Manage workstation ergonomics and Work comfortably at your computer Ikon services.
A12: Catering - in scope with conditions | B12: To answer briefly: the funding may be used for catering where the expenditure complies with the Expenditure on Hospitality procedures and is related to a principal wellbeing activity. Please note that catering alone is not a principal wellbeing activity - it needs to be connected to an eligible wellbeing activity.

Sheet Reference links
B2: Reference links
B4: Topic | C4: Link
B5: Spend principal wellbeing targeted funding (decision-making framework) | C5: https://ikon.education.wa.edu.au/-/spend-principal-wellbeing-targeted-funding
B6: Examples of using the decision-making framework | C6: https://ikon.education.wa.edu.au/-/examples-of-using-the-decision-making-framework-for-wellbeing-expenditure-decisions/
B7: Integrity framework | C7: https://ikon.education.wa.edu.au/-/integrity-framework/
B8: Our Code of Conduct and standards | C8: https://ikon.education.wa.edu.au/-/our-code-of-conduct-and-standards/
B9: Report a conflict of interest | C9: https://ikon.education.wa.edu.au/-/declare-a-conflict-of-interest
B10: Access the Employee Assistance Program | C10: https://ikon.education.wa.edu.au/-/access-the-employee-assistance-program
B11: AHPRA practitioner register | C11: https://www.ahpra.gov.au/
B12: Buy goods and services under $50,000 | C12: https://ikon.education.wa.edu.au/-/buy-goods-and-services-under-50-000
B13: Follow the rules for buying goods and services | C13: https://ikon.education.wa.edu.au/-/follow-rules-for-buying-goods-and-services
B14: Official Travel Policy | C14: https://www.education.wa.edu.au/web/policies/-/official-travel-policy
B15: Official Air Travel procedures | C15: https://www.education.wa.edu.au/web/policies/-/official-air-travel-procedures
... B19: Tenders WA (panel tender information for providers) | C19: https://www.tenders.wa.gov.au/

Sheet Lists
A1: Greetings | B1: Answers | C1: Response types | F1: Logic
A2: Good morning | B2: Yes | C2: Build from the framework questions | F2: =TRIM(IF('Email builder'!$D$6="","Hi",'Email builder'!$D$6)&" "&TRIM('Email builder'!$D$7))&"," | G2: ='Email builder'!$D$16 | H2: =IF(G2="","",IFERROR(T(INDEX('Response library'!$D$5:$D$28,MATCH("Q1|"&G2,'Response library'!$E$5:$E$28,0))),""))
A3: Good afternoon | B3: No | C3: =IF('Common responses'!A5="","",'Common responses'!A5) | F3: =IF(TRIM('Email builder'!$D$8)="","Thank you for reaching out regarding the principal wellbeing targeted funding.","Thank you for reaching out regarding "&TRIM('Email builder'!$D$8)&".") | G3: ='Email builder'!$D$17 | H3: =IF(G3="","",IFERROR(T(INDEX('Response library'!$D$5:$D$28,MATCH("Q2|"&G3,'Response library'!$E$5:$E$28,0))),""))
A4: Good evening | B4: Maybe | C4: =IF('Common responses'!A6="","",'Common responses'!A6) | G4: ='Email builder'!$D$18 | H4: =IF(G4="","",IFERROR(T(INDEX('Response library'!$D$5:$D$28,MATCH("Q3|"&G4,'Response library'!$E$5:$E$28,0))),""))
A5: Hi | C5: =IF('Common responses'!A7="","",'Common responses'!A7) | F5: =COUNTIF(G2:G7,"?*") | G5: ='Email builder'!$D$19 | H5: =IF(G5="","",IFERROR(T(INDEX('Response library'!$D$5:$D$28,MATCH("Q4|"&G5,'Response library'!$E$5:$E$28,0))),""))
C6: =IF('Common responses'!A8="","",'Common responses'!A8) | F6: =IF(F5=0,"",IF(COUNTIF(G2:G7,"No")>0,"To answer briefly: based on the decision-making framework, this expenditure does not appear to be appropriate. Please see the detail below.",IF(COUNTIF(G2:G7,"Yes")=6,"To answer briefly: based on the decision-making framework, this expenditure is likely to be appropriate. Please see the detail below.","To answer briefly: we need a little more information before this expenditure can be confirmed as appropriate. Please see the detail below."))) | G6: ='Email builder'!$D$20 | H6: =IF(G6="","",IFERROR(T(INDEX('Response library'!$D$5:$D$28,MATCH("Q5|"&G6,'Response library'!$E$5:$E$28,0))),""))
C7: =IF('Common responses'!A9="","",'Common responses'!A9) | F7: =IF(F5=0,"",_xlfn.TEXTJOIN(CHAR(10)&CHAR(10),TRUE,F6,"To answer more thoroughly:",H2:H9)) | G7: ='Email builder'!$D$21 | H7: =IF(G7="","",IFERROR(T(INDEX('Response library'!$D$5:$D$28,MATCH("Q6|"&G7,'Response library'!$E$5:$E$28,0))),""))
C8: =IF('Common responses'!A10="","",'Common responses'!A10) | F8: ='Email builder'!$D$11 | G8: ='Email builder'!$D$23 | H8: =IF(G8="","",IFERROR(T(INDEX('Response library'!$D$5:$D$28,MATCH("Panel|"&G8,'Response library'!$E$5:$E$28,0))),""))
C9: =IF('Common responses'!A11="","",'Common responses'!A11) | F9: =IF(OR(F8="",F8="Build from the framework questions"),"",IFERROR(T(INDEX('Common responses'!$B$5:$B$12,MATCH(F8,'Common responses'!$A$5:$A$12,0))),"")) | G9: ='Email builder'!$D$24 | H9: =IF(G9="","",IFERROR(T(INDEX('Response library'!$D$5:$D$28,MATCH("Travel|"&G9,'Response library'!$E$5:$E$28,0))),""))
C10: =IF('Common responses'!A12="","",'Common responses'!A12) | F10: =IF(F9<>"",F9,IF(F5=0,"[Pick a common response in Step 2, or answer the framework questions in Step 3, to build the body of your email.]",F7))
F11: ="If you have any further questions, please reach out again. You can contact Principal wellbeing expenditure support by phone on 9264 4201 or by email at whsw.staffwellbeing@education.wa.edu.au."
F12: =F2&CHAR(10)&CHAR(10)&F3&CHAR(10)&CHAR(10)&F10&CHAR(10)&CHAR(10)&F11&CHAR(10)&CHAR(10)&"Kind regards,"
F13: =IF(F9<>"","Common response selected: "&F8,IF(F5=0,"Waiting for answers - pick a common response (Step 2) or answer the questions (Step 3).",IF(F5<6,"Keep going - "&F5&" of 6 framework questions answered. The draft below updates as you go.",IF(COUNTIF(G2:G7,"No")>0,"Likely NOT appropriate - recommend reconsidering or contacting the team.",IF(COUNTIF(G2:G7,"Yes")=6,"Likely appropriate to proceed.","Needs more information - recommend contacting Principal wellbeing expenditure support.")))))
