Workbook
Name Slicer_CommonResponse: #N/A
Name Slicer_Panel: #N/A
Name Slicer_Q1: #N/A
Name Slicer_Q2: #N/A
Name Slicer_Q3: #N/A
Name Slicer_Q4: #N/A
Name Slicer_Q5: #N/A
Name Slicer_Q6: #N/A
Name Slicer_Travel: #N/A

Sheet Interactive triage
B2: Principal wellbeing query triage
B4: Select Yes, No or Maybe in the question slicers below - you do not need to answer every question; unanswered ones are simply left out of the draft. For recurring queries, pick a common response override instead. Then add a greeting, name and topic under 'Draft email reply' and copy the finished draft into Outlook. To clear a slicer, click the funnel-with-x button in its top right corner.
B7: Select responses
B27: Triage result
B28: =IF('Preset responses'!$F$2<>"","Common response override selected: "&'Preset responses'!$E$2,IF(COUNTIF('Pivot source data'!$J$40:$Q$40,"?*")=0,"Waiting for answers - select Yes, No or Maybe in any question slicer, or pick a common response override.",IF(COUNTIF('Pivot source data'!$J$40:$O$40,"No")>0,"Likely NOT appropriate - recommend reconsidering or contacting the team.",IF(COUNTIF('Pivot source data'!$J$40:$O$40,"Yes")=6,"Likely appropriate to proceed.","Based on the answers so far, more information is needed - unanswered questions are left out of the draft."))))
B32: Draft email reply
B33: Greeting & recipient name | D33: Good morning | G33: Pick a greeting and add a name, e.g. 'Good morning Damien,'
B34: Topic of the query (optional) | G34: Completes "Thank you for reaching out regarding ...", e.g. "using the funding for physiotherapy"
B35: =TRIM(IF($D$33="","Hi",$D$33)&" "&TRIM($E$33))&","&CHAR(10)&CHAR(10)&IF(TRIM($D$34)="","Thank you for reaching out regarding the principal wellbeing targeted funding.","Thank you for reaching out regarding "&TRIM($D$34)&".")&CHAR(10)&CHAR(10)&IF('Preset responses'!$F$2<>"",'Preset responses'!$F$2,IF(COUNTIF('Pivot source data'!$J$40:$Q$40,"?*")=0,"[Select an answer in one or more question slicers above, or pick a common response override, to build the body of the email.]",IF('Pivot source data'!$AA$40="","[The answers selected so far do not add any wording to the email - answer more of the question slicers above.]",'Pivot source data'!$AA$40)))&CHAR(10)&CHAR(10)&"If you have any further questions, please reach out again. You can contact Principal wellbeing expenditure support by phone on 9264 4201 or by email at whsw.staffwellbeing@education.wa.edu.au."&CHAR(10)&CHAR(10)&"Kind regards,"
B54: Edit the modular wording on the Response library tab and the recurring full responses on the Preset responses tab. The draft remains a starting point: add case-specific detail and confirm the final advice against current Ikon guidance before sending.

Sheet Select answers
B2: Principal wellbeing query triage tool
B4: How to use this tool: answer the six decision-making framework questions for the query you are triaging, then add whether it aligns with the panel and whether it involves travel. Open the 'Draft reply' tab to see the assessment and a draft response update automatically. This tool supports professional judgement. It does not replace it.
B10: Decision-making framework
B12: Q1. Will this directly benefit my health, wellbeing or both as a principal?
B14: Q2. Does this align with the priorities in the health and wellbeing strategies or panel service categories?
B16: Q3. Would this expenditure uphold Department values and standards, as per the Integrity framework and Code of Conduct?
B18: Q4. Is the provider reputable, appropriately insured and qualified to deliver the service?
B20: Q5. Does this service meet a need that cannot be provided for by current Department programs or services?
B22: Q6. Have all supplier-related conflicts of interest been identified, reported and appropriately managed (or do none apply)?
B25: Additional routing questions
B27: Does this align with the panel of wellbeing service providers?
B29: Does this involve travel or accommodation?
B32: Tip: to clear a slicer, select the small red 'X' funnel button in its top right corner.

Sheet Draft reply
B2: Draft reply
B4: This updates automatically from the 'Select answers' tab. Use it as a starting point for your reply and adjust the wording to fit the query.
B7: Overall assessment
B8: =IF(IF('Select answers'!C12="",1,0)+IF('Select answers'!C14="",1,0)+IF('Select answers'!C16="",1,0)+IF('Select answers'!C18="",1,0)+IF('Select answers'!C20="",1,0)+IF('Select answers'!C22="",1,0)>0,"Answer all six decision-making framework questions on the Select answers tab to generate an assessment.",IF(IF('Select answers'!C12="No",1,0)+IF('Select answers'!C14="No",1,0)+IF('Select answers'!C16="No",1,0)+IF('Select answers'!C18="No",1,0)+IF('Select answers'!C20="No",1,0)+IF('Select answers'!C22="No",1,0)>0,"Likely not appropriate. Contact the Principal Wellbeing Consultant before proceeding.",IF(IF('Select answers'!C12="Yes",1,0)+IF('Select answers'!C14="Yes",1,0)+IF('Select answers'!C16="Yes",1,0)+IF('Select answers'!C18="Yes",1,0)+IF('Select answers'!C20="Yes",1,0)+IF('Select answers'!C22="Yes",1,0)=6,"Likely appropriate to proceed.","Needs more information before this can be confirmed. Contact the Principal Wellbeing Consultant."))) -> Answer all six decision-making framework questions on the Select answers tab to generate an assessment.
B11: Basis for this assessment
B12: Question | C12: Your answer | D12: Draft paragraph
B13: Q1: Will this directly benefit my health, wellbeing or both as a principal? | C13: =IF('Select answers'!C12="","",'Select answers'!C12) | D13: =IF('Select answers'!C12="","",IFERROR(INDEX('Response library'!$D:$D,MATCH("Q1|"&'Select answers'!C12,'Response library'!$E:$E,0)),""))
B14: Q2: Does this align with the priorities in the health and wellbeing strategies or panel service categories? | C14: =IF('Select answers'!C14="","",'Select answers'!C14) | D14: =IF('Select answers'!C14="","",IFERROR(INDEX('Response library'!$D:$D,MATCH("Q2|"&'Select answers'!C14,'Response library'!$E:$E,0)),""))
B15: Q3: Would this expenditure uphold Department values and standards, as per the Integrity framework and Code of Conduct? | C15: =IF('Select answers'!C16="","",'Select answers'!C16) | D15: =IF('Select answers'!C16="","",IFERROR(INDEX('Response library'!$D:$D,MATCH("Q3|"&'Select answers'!C16,'Response library'!$E:$E,0)),""))
B16: Q4: Is the provider reputable, appropriately insured and qualified to deliver the service? | C16: =IF('Select answers'!C18="","",'Select answers'!C18) | D16: =IF('Select answers'!C18="","",IFERROR(INDEX('Response library'!$D:$D,MATCH("Q4|"&'Select answers'!C18,'Response library'!$E:$E,0)),""))
B17: Q5: Does this service meet a need that cannot be provided for by current Department programs or services? | C17: =IF('Select answers'!C20="","",'Select answers'!C20) | D17: =IF('Select answers'!C20="","",IFERROR(INDEX('Response library'!$D:$D,MATCH("Q5|"&'Select answers'!C20,'Response library'!$E:$E,0)),""))
B18: Q6: Have all supplier-related conflicts of interest been identified, reported and appropriately managed (or do none apply)? | C18: =IF('Select answers'!C22="","",'Select answers'!C22) | D18: =IF('Select answers'!C22="","",IFERROR(INDEX('Response library'!$D:$D,MATCH("Q6|"&'Select answers'!C22,'Response library'!$E:$E,0)),""))
B19: Does this align with the panel of wellbeing service providers? | C19: =IF('Select answers'!C27="","",'Select answers'!C27) | D19: =IF('Select answers'!C27="","",IFERROR(INDEX('Response library'!$D:$D,MATCH("Panel|"&'Select answers'!C27,'Response library'!$E:$E,0)),""))
B20: Does this involve travel or accommodation? | C20: =IF('Select answers'!C29="","",'Select answers'!C29) | D20: =IF('Select answers'!C29="","",IFERROR(INDEX('Response library'!$D:$D,MATCH("Travel|"&'Select answers'!C29,'Response library'!$E:$E,0)),""))
B23: Draft reply text
B24: =_xlfn.TEXTJOIN(CHAR(10)&CHAR(10),TRUE(),B8,D13,D14,D15,D16,D17,D18,D19,D20) -> Answer all six decision-making framework questions on the Select answers tab to generate an assessment.

Sheet Pivot source data
A1: Q1 | B1: Visible row
A2: Yes | B2: =SUBTOTAL(103,A2)
A3: No | B3: =SUBTOTAL(103,A3)
A4: Maybe | B4: =SUBTOTAL(103,A4)
A6: Q2 | B6: Visible row
A7: Yes | B7: =SUBTOTAL(103,A7)
A8: No | B8: =SUBTOTAL(103,A8)
A9: Maybe | B9: =SUBTOTAL(103,A9)
A11: Q3 | B11: Visible row
A12: Yes | B12: =SUBTOTAL(103,A12)
A13: No | B13: =SUBTOTAL(103,A13)
A14: Maybe | B14: =SUBTOTAL(103,A14)
A16: Q4 | B16: Visible row
A17: Yes | B17: =SUBTOTAL(103,A17)
A18: No | B18: =SUBTOTAL(103,A18)
A19: Maybe | B19: =SUBTOTAL(103,A19)
A21: Q5 | B21: Visible row
A22: Yes | B22: =SUBTOTAL(103,A22)
A23: No | B23: =SUBTOTAL(103,A23)
A24: Maybe | B24: =SUBTOTAL(103,A24)
A26: Q6 | B26: Visible row
A27: Yes | B27: =SUBTOTAL(103,A27)
A28: No | B28: =SUBTOTAL(103,A28)
A29: Maybe | B29: =SUBTOTAL(103,A29)
A31: Panel | B31: Visible row
A32: Yes | B32: =SUBTOTAL(103,A32)
A33: No | B33: =SUBTOTAL(103,A33)
A34: Maybe | B34: =SUBTOTAL(103,A34)
A36: Travel | B36: Visible row
A37: Yes | B37: =SUBTOTAL(103,A37)
A38: No | B38: =SUBTOTAL(103,A38)
A39: Maybe | B39: =SUBTOTAL(103,A39) | J39: Selected Q1 | K39: Selected Q2 | L39: Selected Q3 | M39: Selected Q4 | N39: Selected Q5 | O39: Selected Q6 | P39: Selected Panel | Q39: Selected Travel | R39: Q1 paragraph | S39: Q2 paragraph | T39: Q3 paragraph | U39: Q4 paragraph | V39: Q5 paragraph | W39: Q6 paragraph | X39: Panel paragraph | Y39: Travel paragraph | Z39: Overall assessment | AA39: Combined draft body
J40: =IF(SUM($B$2:$B$4)=1,INDEX($A$2:$A$4,MATCH(1,$B$2:$B$4,0)),"") | K40: =IF(SUM($B$7:$B$9)=1,INDEX($A$7:$A$9,MATCH(1,$B$7:$B$9,0)),"") | L40: =IF(SUM($B$12:$B$14)=1,INDEX($A$12:$A$14,MATCH(1,$B$12:$B$14,0)),"") | M40: =IF(SUM($B$17:$B$19)=1,INDEX($A$17:$A$19,MATCH(1,$B$17:$B$19,0)),"") | N40: =IF(SUM($B$22:$B$24)=1,INDEX($A$22:$A$24,MATCH(1,$B$22:$B$24,0)),"") | O40: =IF(SUM($B$27:$B$29)=1,INDEX($A$27:$A$29,MATCH(1,$B$27:$B$29,0)),"") | P40: =IF(SUM($B$32:$B$34)=1,INDEX($A$32:$A$34,MATCH(1,$B$32:$B$34,0)),"") | Q40: =IF(SUM($B$37:$B$39)=1,INDEX($A$37:$A$39,MATCH(1,$B$37:$B$39,0)),"") | R40: =IF($J$40="","",IFERROR(INDEX('Response library'!$D$2:$D$24,MATCH("Q1|"&$J$40,'Response library'!$E$2:$E$24,0)),"")) | S40: =IF($K$40="","",IFERROR(INDEX('Response library'!$D$2:$D$24,MATCH("Q2|"&$K$40,'Response library'!$E$2:$E$24,0)),"")) | T40: =IF($L$40="","",IFERROR(INDEX('Response library'!$D$2:$D$24,MATCH("Q3|"&$L$40,'Response library'!$E$2:$E$24,0)),"")) | U40: =IF($M$40="","",IFERROR(INDEX('Response library'!$D$2:$D$24,MATCH("Q4|"&$M$40,'Response library'!$E$2:$E$24,0)),"")) | V40: =IF($N$40="","",IFERROR(INDEX('Response library'!$D$2:$D$24,MATCH("Q5|"&$N$40,'Response library'!$E$2:$E$24,0)),"")) | W40: =IF($O$40="","",IFERROR(INDEX('Response library'!$D$2:$D$24,MATCH("Q6|"&$O$40,'Response library'!$E$2:$E$24,0)),"")) | X40: =IF($P$40="","",IFERROR(INDEX('Response library'!$D$2:$D$24,MATCH("Panel|"&$P$40,'Response library'!$E$2:$E$24,0)),"")) | Y40: =IF($Q$40="","",IFERROR(T(INDEX('Response library'!$D$2:$D$25,MATCH("Travel|"&$Q$40,'Response library'!$E$2:$E$25,0))),"")) | Z40: =IF(COUNTIF($J$40:$O$40,"?*")=0,"",IF(COUNTIF($J$40:$O$40,"No")>0,"To answer briefly: based on the decision-making framework, this expenditure does not appear to be appropriate. Please see the detail below.",IF(COUNTIF($J$40:$O$40,"Yes")=6,"To answer briefly: based on the decision-making framework, this expenditure is likely to be appropriate. Please see the detail below.","To answer briefly: we need a little more information before this expenditure can be confirmed as appropriate. Please see the detail below."))) | AA40: =IF(COUNTIF($J$40:$Q$40,"?*")=0,"",_xlfn.TEXTJOIN(CHAR(10)&CHAR(10),TRUE(),$Z$40,IF(COUNTIF($J$40:$O$40,"?*")=0,"","To answer more thoroughly:"),$R$40:$Y$40))

Sheet Reference links
B2: Reference links
B4: Topic | C4: Link
B5: Spend principal wellbeing targeted funding (decision-making framework) | C5: https://ikon.education.wa.edu.au/-/spend-principal-wellbeing-targeted-funding
B6: Examples of using the decision-making framework | C6: https://ikon.education.wa.edu.au/-/examples-of-using-the-decision-making-framework-for-wellbeing-expenditure-decisions/
B7: Integrity framework | C7: https://ikon.education.wa.edu.au/-/integrity-framework/
B8: Our Code of Conduct and standards | C8: https://ikon.education.wa.edu.au/-/our-code-of-conduct-and-standards/
B9: Report a conflict of interest | C9: https://ikon.education.wa.edu.au/-/declare-a-conflict-of-interest
B10: Access the Employee Assistance Program | C10: https://ikon.education.wa.edu.au/-/access-the-employee-assistance-program
B11: AHPRA practitioner register | C11: https://www.ahpra.gov.au/
B12: Buy goods and services under $50,000 | C12: https://ikon.education.wa.edu.au/-/buy-goods-and-services-under-50-000
B13: Follow the rules for buying goods and services | C13: https://ikon.education.wa.edu.au/-/follow-rules-for-buying-goods-and-services
B14: Official Travel Policy | C14: https://www.education.wa.edu.au/web/policies/-/official-travel-policy
B15: Manage accounting records | C15: https://ikon.education.wa.edu.au/-/manage-accounting-records
... B19: Tenders WA (panel tender information for providers) | C19: https://www.tenders.wa.gov.au/

Sheet Response library
A1: Question code | B1: Question | C1: Answer | D1: Draft email paragraph — edit this yellow column | E1: Lookup key — do not edit
A2: Q1 | B2: Will this directly benefit my health, wellbeing or both as a principal? | C2: Yes | D2: The proposed expenditure meets the first test of the decision-making framework: it is intended to directly benefit your health, wellbeing or both as a principal. | E2: =A2&"|"&C2 -> Q1|Yes
A3: Q1 | B3: Will this directly benefit my health, wellbeing or both as a principal? | C3: No | D3: The proposed expenditure does not appear to directly benefit your health or wellbeing as a principal. The targeted funding is to address your needs as a principal - it is not intended for staff wellbeing or general operating costs - so we recommend reconsidering this expenditure. | E3: =A3&"|"&C3 -> Q1|No
A4: Q1 | B4: Will this directly benefit my health, wellbeing or both as a principal? | C4: Maybe | D4: It is not clear that this would directly benefit your health or wellbeing as a principal. We would be happy to talk this through with you before you proceed. | E4: =A4&"|"&C4 -> Q1|Maybe
A5: Q2 | B5: Does this align with the priorities in the health and wellbeing strategies or panel service categories? | C5: Yes | D5: It aligns with the priorities in the health and wellbeing strategies and the panel service categories (executive and leadership coaching, executive health assessment, and mental health support). | E5: =A5&"|"&C5 -> Q2|Yes
A6: Q2 | B6: Does this align with the priorities in the health and wellbeing strategies or panel service categories? | C6: No | D6: It does not align with the priorities in the health and wellbeing strategies or the panel service categories, so we recommend reconsidering this expenditure. | E6: =A6&"|"&C6 -> Q2|No
A7: Q2 | B7: Does this align with the priorities in the health and wellbeing strategies or panel service categories? | C7: Maybe | D7: The alignment with the health and wellbeing strategies or the panel service categories is not clear - please check with us before proceeding. | E7: =A7&"|"&C7 -> Q2|Maybe
A8: Q3 | B8: Would this expenditure uphold Department values and standards, as per the Integrity framework and Code of Conduct? | C8: Yes | D8: The expenditure would uphold Department values and standards, in line with our Integrity framework and Code of Conduct (including Standard 8 - use public resources responsibly). | E8: =A8&"|"&C8 -> Q3|Yes
A9: Q3 | B9: Would this expenditure uphold Department values and standards, as per the Integrity framework and Code of Conduct? | C9: No | D9: The expenditure does not appear to uphold Department values and standards under the Integrity framework and Code of Conduct, so we recommend reconsidering it. | E9: =A9&"|"&C9 -> Q3|No
A10: Q3 | B10: Would this expenditure uphold Department values and standards, as per the Integrity framework and Code of Conduct? | C10: Maybe | D10: It is not clear that the expenditure would uphold Department values and standards under the Integrity framework and Code of Conduct - please contact us before proceeding. | E10: =A10&"|"&C10 -> Q3|Maybe
A11: Q4 | B11: Is the provider reputable, appropriately insured and qualified to deliver the service? | C11: Yes | D11: The provider is reputable, appropriately insured and qualified to deliver the service. | E11: =A11&"|"&C11 -> Q4|Yes
A12: Q4 | B12: Is the provider reputable, appropriately insured and qualified to deliver the service? | C12: No | D12: The provider's qualifications, insurance or reputation cannot be confirmed, so please do not proceed until this is resolved. Information about managing provider risks is available in the Develop a staff health and wellbeing plan Ikon service. | E12: =A12&"|"&C12 -> Q4|No
A13: Q4 | B13: Is the provider reputable, appropriately insured and qualified to deliver the service? | C13: Maybe | D13: The provider's qualifications, insurance or reputation have not yet been confirmed. Where relevant, check the Australian Health Practitioner Regulation Agency (AHPRA) register and confirm the provider's insurance before proceeding. | E13: =A13&"|"&C13 -> Q4|Maybe
... A23: Travel | B23: Does this involve travel or accommodation? | C23: Yes | D23: As the query involves travel or accommodation: the funding may be used for travel and accommodation where it is required to support access to an eligible principal wellbeing activity, in line with the Official Travel Policy and the associated Official Air Travel and Travel Accommodation, Meal and Other Expenses procedures. Travellers cannot approve their own travel - please seek approval from an Assistant Director of Education or above prior to booking. The funding is not intended to be used solely for travel or accommodation. | E23: =A23&"|"&C23 -> Travel|Yes
A24: Travel | B24: Does this involve travel or accommodation? | C24: No | E24: =A24&"|"&C24 -> Travel|No
A25: Travel | B25: Does this involve travel or accommodation? | C25: Maybe | D25: It is not yet clear whether travel or accommodation will be involved. If it is, it may be funded where it supports the eligible wellbeing activity, in line with the Official Travel Policy - please check the approval requirements with us before booking. | E25: =A25&"|"&C25

Sheet Preset responses
A1: Common response overrides | E1: Selected option | F1: Selected response
A2: Edit the response names or the yellow response text below. These options appear as buttons on the common response override slicer on the Interactive triage tab. | E2: =IF(SUM(PresetResponses[Visible row])=1,INDEX(PresetResponses[Response option],MATCH(1,PresetResponses[Visible row],0)),"") | F2: =IF(OR(E2="",E2="Use standard triage response"),"",INDEX(PresetResponses[Draft email body],MATCH(E2,PresetResponses[Response option],0)))
A3: Clear the optional override slicer, or select “Use standard triage response”, to return to the question-based draft. If a new option does not appear immediately, save and reopen the workbook.
A5: Response option | B5: Draft email body | C5: Visible row
A6: Use standard triage response | C6: =SUBTOTAL(103,A6) -> 0
A7: Treatments / physiotherapy | B7: To answer briefly: no - personal health care, treatments and therapies (including physiotherapy and chiropractic care) are not within the scope of the targeted wellbeing funding. To answer more thoroughly: The Workers' Compensation and Injury Management Act 2023 (WA) prohibits employers from diverting workers away from making a claim, so wellbeing funds cannot be used for injury-related assessment or treatment services. Treatment for work-related pain or injury may be available through the workers' compensation process, and may include payment for expenses, loss of earnings or both. Personal medical expenses are considered a fringe benefit. While this service falls outside the scope of the funding, there are a range of other services you may wish to consider, including professional learning and resilience training, mental health support or pastoral care, coaching or mentoring (including executive and wellbeing coaching), and executive health and wellbeing assessments. | C7: =SUBTOTAL(103,A7)
A8: Memberships, gym or devices | B8: To answer briefly: no - memberships (such as gym or Pilates memberships), goods and personal devices are for the personal benefit of the employee, are considered a fringe benefit, and are not within the scope of the targeted wellbeing funding. You may instead wish to consider services such as professional learning and resilience training, mental health support or pastoral care, coaching or mentoring (including executive and wellbeing coaching), or an executive health and wellbeing assessment. | C8: =SUBTOTAL(103,A8)
A9: Travel & accommodation | B9: To answer briefly: yes - the wellbeing funding can be used toward travel and accommodation needed to support access to an eligible wellbeing activity (such as professional learning, a professional conference or similar). To answer more thoroughly: The funding may be used for travel and accommodation where the travel is required to support the wellbeing activity. It is not intended to be used solely for travel or accommodation. Travel needs to align with the Official Travel Policy and the associated Official Air Travel and Travel Accommodation, Meal and Other Expenses procedures. Travellers cannot approve their own travel: per the Travel Approval Schedule, please seek approval from an Assistant Director of Education or above prior to booking. For domestic air travel, the domestic air travel application form must be completed and approved before booking. | C9: =SUBTOTAL(103,A9)
A10: Conference / professional learning | B10: To answer briefly: yes - conferences and professional learning are considered appropriate expenditure where the majority of the program focuses on enhancing leadership capability and includes wellbeing topics for executives. To answer more thoroughly: Suitable themes include work-related stress reduction, managing workload and role overload, resilience skills for leaders, decision-making under stress, and high-performance leadership without burnout. The targeted funding may complement your school's budget allocation for the principal's professional learning, and relevant travel costs, but it should not replace it. If travel is required to attend, it needs to align with the Official Travel Policy and associated procedures, with approval from an Assistant Director of Education or above prior to booking. | C10: =SUBTOTAL(103,A10)
A11: Pooling funding with schools | B11: To answer briefly: yes - you may choose to pool your wellbeing funding with other schools, such as those in your school network, to access higher cost support services (for example, leadership or wellbeing coaching). To answer more thoroughly: The decision-making framework applies to pooled funding in the same way as individual funding. You can choose an appropriate budget account or accounts to record the transfer of funds when pooling resources. For purchases under $50,000, follow the Buy goods and services under $50,000 Ikon service - the Verbal quotation template or Very simple purchase template may be useful. Purchases of less than $5,000 are considered low-value procurements and a panel is not required, provided value for money has been considered. | C11: =SUBTOTAL(103,A11)
A12: Recording purchases / acquittal | B12: To answer briefly: expenditure only needs to be lodged through Oracle, and you can choose an appropriate budget account or accounts to record purchases against. We do not monitor principal wellbeing expenditure, and you do not need to provide formal acquittal reports. We do encourage you to keep a record of your decisions to demonstrate accountable and ethical decision-making - the Manage school accounting records Ikon service provides guidance on record keeping. | C12: =SUBTOTAL(103,A12)
A13: Ergonomic equipment | B13: To answer briefly: ergonomic assessments and equipment are provided for in existing school funding, so they sit outside the targeted wellbeing funding. For guidance, refer to the Manage workstation ergonomics and Work comfortably at your computer Ikon services. | C13: =SUBTOTAL(103,A13)
A14: Catering | B14: To answer briefly: the funding may be used for catering where the expenditure complies with the Expenditure on Hospitality procedures and is related to a principal wellbeing activity. Please note that catering alone is not a principal wellbeing activity - it needs to be connected to an eligible wellbeing activity. | C14: =SUBTOTAL(103,A14)
